LICENSE.rst
MANIFEST.in
README.rst
setup.py
src/bda/__init__.py
src/bda.recipe.deployment.egg-info/PKG-INFO
src/bda.recipe.deployment.egg-info/SOURCES.txt
src/bda.recipe.deployment.egg-info/dependency_links.txt
src/bda.recipe.deployment.egg-info/entry_points.txt
src/bda.recipe.deployment.egg-info/namespace_packages.txt
src/bda.recipe.deployment.egg-info/not-zip-safe
src/bda.recipe.deployment.egg-info/requires.txt
src/bda.recipe.deployment.egg-info/top_level.txt
src/bda/recipe/__init__.py
src/bda/recipe/deployment/__init__.py
src/bda/recipe/deployment/command.py
src/bda/recipe/deployment/common.py
src/bda/recipe/deployment/common.rst
src/bda/recipe/deployment/env.py
src/bda/recipe/deployment/git.py
src/bda/recipe/deployment/git.rst
src/bda/recipe/deployment/main.py
src/bda/recipe/deployment/main.rst
src/bda/recipe/deployment/recipe.py
src/bda/recipe/deployment/svn.py
src/bda/recipe/deployment/svn.rst
src/bda/recipe/deployment/tests.py