Metadata-Version: 1.1
Name: bda.recipe.deployment
Version: 2.0b8
Summary: python deployment process based on buildout and mr.developer
Home-page: http://pypi.python.org/pypi/bda.recipe.deployment
Author: BlueDynamics Alliance
Author-email: dev@bluedynamics.com
License: GPLv2
Platform: UNKNOWN
Classifier: License :: OSI Approved :: GNU General Public License (GPL)
Classifier: Operating System :: OS Independent
Classifier: Programming Language :: Python
Classifier: Topic :: Software Development
